brain_feature_extractor/BrainFeatureExtractorGMM.py
brain_feature_extractor/ExtractorGMM.py
brain_feature_extractor/GaussianMixtureModel.py
brain_feature_extractor/__init__.py
brain_radiodensity_feature_extractor-0.1.1.dist-info/METADATA
brain_radiodensity_feature_extractor-0.1.1.dist-info/WHEEL
brain_radiodensity_feature_extractor-0.1.1.dist-info/top_level.txt
brain_radiodensity_feature_extractor-0.1.1.dist-info/RECORD
