Metadata-Version: 2.1
Name: brain-radiodensity-feature-extractor
Version: 0.1.1
Summary: A simple library that extracts brain features from a Brain Tomography.
Home-page: https://brain-radiodensity-feature-extractor.readthedocs.io/
Author: Williana Leite
Author-email: willianaluziasousaleite@gmail.com
License: MIT
Classifier: Intended Audience :: Developers
Classifier: License :: OSI Approved :: MIT License
Classifier: Programming Language :: Python
Classifier: Programming Language :: Python :: 3
Classifier: Programming Language :: Python :: 3.6
Classifier: Programming Language :: Python :: 3.7
Classifier: Programming Language :: Python :: 3.8
Classifier: Programming Language :: Python :: 3.9
Classifier: Operating System :: OS Independent
Requires-Dist: pytest
Requires-Dist: scikit-learn
Requires-Dist: scipy
Requires-Dist: pydicom
Requires-Dist: pandas
Requires-Dist: numpy
Requires-Dist: opencv-python
Requires-Dist: pyyaml
